{"data":[{"id":1,"name":{"id":"12330"},"icon":"Icon_LoungeFunctionDesk_Gift","open":1,"sort":1,"unlockid":15000},{"id":2,"name":{"id":"12331"},"icon":"Icon_LoungeFunctionDesk_Furniture","open":1,"sort":2,"unlockid":15000},{"id":3,"name":{"id":"12332"},"icon":"Icon_LoungeFunctionDesk_Remember","open":1,"sort":3,"unlockid":15000},{"id":4,"name":{"id":"12333"},"icon1":"Icon_LoungeFunction_Type_Chat","open1":1,"sort1":1,"billboard":"vfx_lounge_billboard","billboardCoordinate":[-7.853,1.858,1.394],"unlockid":15000},{"id":5,"name":{"id":"12334"},"icon1":"Icon_LoungeFunction_Type_Closet","open1":1,"sort1":2,"billboard":"vfx_lounge_billboard","billboardCoordinate":[-2.4,0.823,7.7],"unlockid":15000},{"id":6,"name":{"id":"12335"},"icon1":"Icon_LoungeFunction_Type_Desk","open1":1,"sort1":3,"billboard":"vfx_lounge_Desk","billboardCoordinate":[-1.76,3.32,6.165],"unlockid":15000},{"id":7,"name":{"id":"12336"},"icon1":"Icon_LoungeFunction_Type_Shelf","open1":1,"sort1":4,"billboard":"vfx_lounge_billboard","billboardCoordinate":[1.78,1.07,7.919],"unlockid":15000},{"id":8,"name":{"id":"12337"},"icon1":"Icon_LoungeFunction_Type_WeaponWall","open1":1,"sort1":5,"billboard":"vfx_lounge_billboard","billboardCoordinate":[-5.08,3.32,7.52],"unlockid":15000},{"id":9,"name":{"id":"12338"},"icon1":"Icon_LoungeFunction_Type_PhotoWall","open1":1,"sort1":6,"billboard":"vfx_lounge_billboard","billboardCoordinate":[-0.1,1.49,7.919],"unlockid":15000},{"id":10,"name":{"id":"12339"},"icon1":"Icon_LoungeFunction_Type_FunctionDesk","open1":1,"sort1":7,"billboard":"vfx_lounge_FunctionDesk","billboardCoordinate":[-5.23,0.7,4.489],"unlockid":15000},{"id":11,"name":{"id":"12340"},"icon1":"Icon_LoungeFunction_Type_Store","open1":1,"sort1":8,"billboard":"vfx_lounge_billboard","billboardCoordinate":[-6.06,0.7,4.489],"unlockid":15000},{"id":12,"name":{"id":"12341"},"icon1":"Icon_LoungeFunction_Type_Locker","open1":1,"sort1":9,"billboard":"vfx_lounge_billboard","billboardCoordinate":[-7.08,1.76,1.64],"unlockid":15000}]}