{"data":[{"talentKeyId":202401,"talentKeyType":1,"isEquip":1,"talentKeyName":{"id":"1079"},"battleSkillId":10240901,"keyName":{"id":"1080"},"keyTips":{"id":"1081"},"gunId":[1024],"capacity":0.05},{"talentKeyId":202402,"talentKeyType":1,"isEquip":1,"talentKeyName":{"id":"1079"},"battleSkillId":10240902,"keyName":{"id":"1082"},"keyTips":{"id":"1083"},"gunId":[1024],"capacity":0.05},{"talentKeyId":202403,"talentKeyType":1,"isEquip":1,"talentKeyName":{"id":"1079"},"battleSkillId":10240905,"keyName":{"id":"1084"},"keyTips":{"id":"1085"},"gunId":[1024],"capacity":0.05,"isSwitch":1,"replaceId":102405},{"talentKeyId":202404,"talentKeyType":1,"isEquip":1,"talentKeyName":{"id":"1079"},"battleSkillId":10240903,"keyName":{"id":"1086"},"keyTips":{"id":"1087"},"gunId":[1024],"capacity":0.05},{"talentKeyId":202405,"talentKeyType":1,"isEquip":1,"talentKeyName":{"id":"1079"},"battleSkillId":10240906,"keyName":{"id":"1088"},"keyTips":{"id":"1089"},"gunId":[1024],"capacity":0.05,"isSwitch":1,"replaceId":102407},{"talentKeyId":202406,"talentKeyType":1,"isEquip":1,"talentKeyName":{"id":"1079"},"battleSkillId":10240904,"keyName":{"id":"1090"},"keyTips":{"id":"1091"},"gunId":[1024],"capacity":0.05},{"talentKeyId":201701,"talentKeyType":1,"isEquip":1,"talentKeyName":{"id":"1079"},"battleSkillId":10170901,"keyName":{"id":"1092"},"keyTips":{"id":"1093"},"gunId":[1017],"capacity":0.05},{"talentKeyId":201702,"talentKeyType":1,"isEquip":1,"talentKeyName":{"id":"1079"},"battleSkillId":10170906,"keyName":{"id":"1094"},"keyTips":{"id":"1095"},"gunId":[1017],"capacity":0.05,"isSwitch":1,"replaceId":101707},{"talentKeyId":201703,"talentKeyType":1,"isEquip":1,"talentKeyName":{"id":"1079"},"battleSkillId":10170903,"keyName":{"id":"1096"},"keyTips":{"id":"1097"},"gunId":[1017],"capacity":0.05},{"talentKeyId":201704,"talentKeyType":1,"isEquip":1,"talentKeyName":{"id":"1079"},"battleSkillId":10170905,"keyName":{"id":"1098"},"keyTips":{"id":"1099"},"gunId":[1017],"capacity":0.05,"isSwitch":1,"replaceId":101705},{"talentKeyId":201705,"talentKeyType":1,"isEquip":1,"talentKeyName":{"id":"1079"},"battleSkillId":10170902,"keyName":{"id":"1100"},"keyTips":{"id":"1101"},"gunId":[1017],"capacity":0.05},{"talentKeyId":201706,"talentKeyType":1,"isEquip":1,"talentKeyName":{"id":"1079"},"battleSkillId":10170904,"keyName":{"id":"1102"},"keyTips":{"id":"1103"},"gunId":[1017],"capacity":0.05},{"talentKeyId":202701,"talentKeyType":1,"isEquip":1,"talentKeyName":{"id":"1079"},"battleSkillId":10270902,"keyName":{"id":"1104"},"keyTips":{"id":"1081"},"gunId":[1027],"capacity":0.05},{"talentKeyId":202702,"talentKeyType":1,"isEquip":1,"talentKeyName":{"id":"1079"},"battleSkillId":10270904,"keyName":{"id":"1105"},"keyTips":{"id":"1106"},"gunId":[1027],"capacity":0.05},{"talentKeyId":202703,"talentKeyType":1,"isEquip":1,"talentKeyName":{"id":"1079"},"battleSkillId":10270903,"keyName":{"id":"1107"},"keyTips":{"id":"1108"},"gunId":[1027],"capacity":0.05},{"talentKeyId":202704,"talentKeyType":1,"isEquip":1,"talentKeyName":{"id":"1079"},"battleSkillId":10270906,"keyName":{"id":"1109"},"keyTips":{"id":"1110"},"gunId":[1027],"capacity":0.05,"isSwitch":1,"replaceId":102707},{"talentKeyId":202705,"talentKeyType":1,"isEquip":1,"talentKeyName":{"id":"1079"},"battleSkillId":10270905,"keyName":{"id":"1111"},"keyTips":{"id":"1112"},"gunId":[1027],"capacity":0.05,"isSwitch":1,"replaceId":102705},{"talentKeyId":202706,"talentKeyType":1,"isEquip":1,"talentKeyName":{"id":"1079"},"battleSkillId":10270901,"keyName":{"id":"1113"},"keyTips":{"id":"1114"},"gunId":[1027],"capacity":0.05},{"talentKeyId":10000,"talentKeyName":{"id":"1115"},"battleSkillId":10000002,"keyName":{"id":"1116"},"keyTips":{"id":"1117"},"gunId":[1001,1008,1009,1015,1017,1022,1023,1013,1021,1024,1025]},{"talentKeyId":200801,"talentKeyType":1,"isEquip":1,"talentKeyName":{"id":"1079"},"battleSkillId":10080901,"keyName":{"id":"1118"},"keyTips":{"id":"1119"},"gunId":[1008],"capacity":0.05},{"talentKeyId":200802,"talentKeyType":1,"isEquip":1,"talentKeyName":{"id":"1079"},"battleSkillId":10080905,"keyName":{"id":"1120"},"keyTips":{"id":"1121"},"gunId":[1008],"capacity":0.05,"isSwitch":1,"replaceId":100805},{"talentKeyId":200803,"talentKeyType":1,"isEquip":1,"talentKeyName":{"id":"1079"},"battleSkillId":10080904,"keyName":{"id":"1122"},"keyTips":{"id":"1123"},"gunId":[1008],"capacity":0.05},{"talentKeyId":200804,"talentKeyType":1,"isEquip":1,"talentKeyName":{"id":"1079"},"battleSkillId":10080906,"keyName":{"id":"1124"},"keyTips":{"id":"1125"},"gunId":[1008],"capacity":0.05,"isSwitch":1,"replaceId":100807},{"talentKeyId":200805,"talentKeyType":1,"isEquip":1,"talentKeyName":{"id":"1079"},"battleSkillId":10080903,"keyName":{"id":"1126"},"keyTips":{"id":"1127"},"gunId":[1008],"capacity":0.05},{"talentKeyId":200806,"talentKeyType":1,"isEquip":1,"talentKeyName":{"id":"1079"},"battleSkillId":10080902,"keyName":{"id":"1128"},"keyTips":{"id":"1129"},"gunId":[1008],"capacity":0.05},{"talentKeyId":201501,"talentKeyType":1,"isEquip":1,"talentKeyName":{"id":"1079"},"battleSkillId":10150902,"keyName":{"id":"1130"},"keyTips":{"id":"1131"},"gunId":[1015],"capacity":0.05},{"talentKeyId":201502,"talentKeyType":1,"isEquip":1,"talentKeyName":{"id":"1079"},"battleSkillId":10150904,"keyName":{"id":"1132"},"keyTips":{"id":"1133"},"gunId":[1015],"capacity":0.05},{"talentKeyId":201503,"talentKeyType":1,"isEquip":1,"talentKeyName":{"id":"1079"},"battleSkillId":10150901,"keyName":{"id":"1134"},"keyTips":{"id":"1135"},"gunId":[1015],"capacity":0.05},{"talentKeyId":201504,"talentKeyType":1,"isEquip":1,"talentKeyName":{"id":"1079"},"battleSkillId":10150903,"keyName":{"id":"1136"},"keyTips":{"id":"1137"},"gunId":[1015],"capacity":0.05},{"talentKeyId":201505,"talentKeyType":1,"isEquip":1,"talentKeyName":{"id":"1079"},"battleSkillId":10150906,"keyName":{"id":"1138"},"keyTips":{"id":"1139"},"gunId":[1015],"capacity":0.05,"isSwitch":1,"replaceId":101507},{"talentKeyId":201506,"talentKeyType":1,"isEquip":1,"talentKeyName":{"id":"1079"},"battleSkillId":10150905,"keyName":{"id":"1140"},"keyTips":{"id":"1141"},"gunId":[1015],"capacity":0.05,"isSwitch":1,"replaceId":101505},{"talentKeyId":200901,"talentKeyType":1,"isEquip":1,"talentKeyName":{"id":"1079"},"battleSkillId":10090903,"keyName":{"id":"1142"},"keyTips":{"id":"1143"},"gunId":[1009],"capacity":0.05},{"talentKeyId":200902,"talentKeyType":1,"isEquip":1,"talentKeyName":{"id":"1079"},"battleSkillId":10090905,"keyName":{"id":"1144"},"keyTips":{"id":"1145"},"gunId":[1009],"capacity":0.05,"isSwitch":1,"replaceId":100905},{"talentKeyId":200903,"talentKeyType":1,"isEquip":1,"talentKeyName":{"id":"1079"},"battleSkillId":10090902,"keyName":{"id":"1146"},"keyTips":{"id":"1147"},"gunId":[1009],"capacity":0.05},{"talentKeyId":200904,"talentKeyType":1,"isEquip":1,"talentKeyName":{"id":"1079"},"battleSkillId":10090906,"keyName":{"id":"1148"},"keyTips":{"id":"1149"},"gunId":[1009],"capacity":0.05,"isSwitch":1,"replaceId":100907},{"talentKeyId":200905,"talentKeyType":1,"isEquip":1,"talentKeyName":{"id":"1079"},"battleSkillId":10090904,"keyName":{"id":"1150"},"keyTips":{"id":"1151"},"gunId":[1009],"capacity":0.05},{"talentKeyId":200906,"talentKeyType":1,"isEquip":1,"talentKeyName":{"id":"1079"},"battleSkillId":10090901,"keyName":{"id":"1152"},"keyTips":{"id":"1153"},"gunId":[1009],"capacity":0.05},{"talentKeyId":202201,"talentKeyType":1,"isEquip":1,"talentKeyName":{"id":"1079"},"battleSkillId":10220901,"keyName":{"id":"1154"},"keyTips":{"id":"1081"},"gunId":[1022],"capacity":0.05},{"talentKeyId":202202,"talentKeyType":1,"isEquip":1,"talentKeyName":{"id":"1079"},"battleSkillId":10220905,"keyName":{"id":"1155"},"keyTips":{"id":"1156"},"gunId":[1022],"capacity":0.05,"isSwitch":1,"replaceId":102205},{"talentKeyId":202203,"talentKeyType":1,"isEquip":1,"talentKeyName":{"id":"1079"},"battleSkillId":10220902,"keyName":{"id":"1157"},"keyTips":{"id":"1158"},"gunId":[1022],"capacity":0.05},{"talentKeyId":202204,"talentKeyType":1,"isEquip":1,"talentKeyName":{"id":"1079"},"battleSkillId":10220904,"keyName":{"id":"1159"},"keyTips":{"id":"1160"},"gunId":[1022],"capacity":0.05},{"talentKeyId":202205,"talentKeyType":1,"isEquip":1,"talentKeyName":{"id":"1079"},"battleSkillId":10220906,"keyName":{"id":"1161"},"keyTips":{"id":"1162"},"gunId":[1022],"capacity":0.05,"isSwitch":1,"replaceId":102207},{"talentKeyId":202206,"talentKeyType":1,"isEquip":1,"talentKeyName":{"id":"1079"},"battleSkillId":10220903,"keyName":{"id":"1163"},"keyTips":{"id":"1164"},"gunId":[1022],"capacity":0.05},{"talentKeyId":202901,"talentKeyType":1,"isEquip":1,"talentKeyName":{"id":"1079"},"battleSkillId":10290902,"keyName":{"id":"1165"},"keyTips":{"id":"1166"},"gunId":[1029],"capacity":0.05},{"talentKeyId":202902,"talentKeyType":1,"isEquip":1,"talentKeyName":{"id":"1079"},"battleSkillId":10290904,"keyName":{"id":"1167"},"keyTips":{"id":"1081"},"gunId":[1029],"capacity":0.05},{"talentKeyId":202903,"talentKeyType":1,"isEquip":1,"talentKeyName":{"id":"1079"},"battleSkillId":10290901,"keyName":{"id":"1168"},"keyTips":{"id":"1169"},"gunId":[1029],"capacity":0.05},{"talentKeyId":202904,"talentKeyType":1,"isEquip":1,"talentKeyName":{"id":"1079"},"battleSkillId":10290903,"keyName":{"id":"1170"},"keyTips":{"id":"1171"},"gunId":[1029],"capacity":0.05},{"talentKeyId":202905,"talentKeyType":1,"isEquip":1,"talentKeyName":{"id":"1079"},"battleSkillId":10290905,"keyName":{"id":"1172"},"keyTips":{"id":"1173"},"gunId":[1029],"capacity":0.05,"isSwitch":1,"replaceId":102905},{"talentKeyId":202906,"talentKeyType":1,"isEquip":1,"talentKeyName":{"id":"1079"},"battleSkillId":10290906,"keyName":{"id":"1174"},"keyTips":{"id":"1175"},"gunId":[1029],"capacity":0.05,"isSwitch":1,"replaceId":102907},{"talentKeyId":202601,"talentKeyType":1,"isEquip":1,"talentKeyName":{"id":"1079"},"battleSkillId":10260901,"keyName":{"id":"1176"},"keyTips":{"id":"1081"},"gunId":[1026],"capacity":0.05},{"talentKeyId":202602,"talentKeyType":1,"isEquip":1,"talentKeyName":{"id":"1079"},"battleSkillId":10260902,"keyName":{"id":"1177"},"keyTips":{"id":"1178"},"gunId":[1026],"capacity":0.05},{"talentKeyId":202603,"talentKeyType":1,"isEquip":1,"talentKeyName":{"id":"1079"},"battleSkillId":10260903,"keyName":{"id":"1179"},"keyTips":{"id":"1180"},"gunId":[1026],"capacity":0.05},{"talentKeyId":202604,"talentKeyType":1,"isEquip":1,"talentKeyName":{"id":"1079"},"battleSkillId":10260906,"keyName":{"id":"1181"},"keyTips":{"id":"1182"},"gunId":[1026],"capacity":0.05,"isSwitch":1,"replaceId":102607},{"talentKeyId":202605,"talentKeyType":1,"isEquip":1,"talentKeyName":{"id":"1079"},"battleSkillId":10260904,"keyName":{"id":"1183"},"keyTips":{"id":"1184"},"gunId":[1026],"capacity":0.05},{"talentKeyId":202606,"talentKeyType":1,"isEquip":1,"talentKeyName":{"id":"1079"},"battleSkillId":10260905,"keyName":{"id":"1185"},"keyTips":{"id":"1186"},"gunId":[1026],"capacity":0.05,"isSwitch":1,"replaceId":102605},{"talentKeyId":901001,"talentKeyType":2,"isEquip":1,"talentKeyName":{"id":"1187"},"propertyId":8000007,"battleSkillId":10010907,"keyName":{"id":"1188"},"keyTips":{"id":"1189"}},{"talentKeyId":901008,"talentKeyType":2,"isEquip":1,"talentKeyName":{"id":"1187"},"propertyId":8000002,"battleSkillId":10080907,"keyName":{"id":"1190"},"keyTips":{"id":"1191"}},{"talentKeyId":901009,"talentKeyType":2,"isEquip":1,"talentKeyName":{"id":"1187"},"propertyId":8000003,"battleSkillId":10090907,"keyName":{"id":"1192"},"keyTips":{"id":"1193"}},{"talentKeyId":901015,"talentKeyType":2,"isEquip":1,"talentKeyName":{"id":"1187"},"propertyId":8000014,"battleSkillId":10150907,"keyName":{"id":"1194"},"keyTips":{"id":"1195"}},{"talentKeyId":901017,"talentKeyType":2,"isEquip":1,"talentKeyName":{"id":"1187"},"propertyId":8000001,"battleSkillId":10170907,"keyName":{"id":"1196"},"keyTips":{"id":"1197"}},{"talentKeyId":901021,"talentKeyType":2,"isEquip":1,"talentKeyName":{"id":"1187"},"propertyId":8000011,"battleSkillId":10210907,"keyName":{"id":"1198"},"keyTips":{"id":"1199"}},{"talentKeyId":901022,"talentKeyType":2,"isEquip":1,"talentKeyName":{"id":"1187"},"propertyId":8000012,"battleSkillId":10220907,"keyName":{"id":"1200"},"keyTips":{"id":"1201"}},{"talentKeyId":901024,"talentKeyType":2,"isEquip":1,"talentKeyName":{"id":"1187"},"propertyId":8000013,"battleSkillId":10240907,"keyName":{"id":"1202"},"keyTips":{"id":"1203"}},{"talentKeyId":901025,"talentKeyType":2,"isEquip":1,"talentKeyName":{"id":"1187"},"propertyId":8000005,"battleSkillId":10250907,"keyName":{"id":"1204"},"keyTips":{"id":"1205"}},{"talentKeyId":901026,"talentKeyType":2,"isEquip":1,"talentKeyName":{"id":"1187"},"propertyId":8000004,"battleSkillId":10260907,"keyName":{"id":"1206"},"keyTips":{"id":"1207"}},{"talentKeyId":901027,"talentKeyType":2,"isEquip":1,"talentKeyName":{"id":"1187"},"propertyId":8000006,"battleSkillId":10270907,"keyName":{"id":"1208"},"keyTips":{"id":"1209"}},{"talentKeyId":901029,"talentKeyType":2,"isEquip":1,"talentKeyName":{"id":"1187"},"propertyId":8000009,"battleSkillId":10290907,"keyName":{"id":"1210"},"keyTips":{"id":"1211"}},{"talentKeyId":200101,"talentKeyType":1,"isEquip":1,"talentKeyName":{"id":"1079"},"battleSkillId":10010904,"keyName":{"id":"1212"},"keyTips":{"id":"1213"},"gunId":[1001],"capacity":0.05},{"talentKeyId":200102,"talentKeyType":1,"isEquip":1,"talentKeyName":{"id":"1079"},"battleSkillId":10010905,"keyName":{"id":"1214"},"keyTips":{"id":"1215"},"gunId":[1001],"capacity":0.05,"isSwitch":1,"replaceId":100105},{"talentKeyId":200103,"talentKeyType":1,"isEquip":1,"talentKeyName":{"id":"1079"},"battleSkillId":10010902,"keyName":{"id":"1216"},"keyTips":{"id":"1217"},"gunId":[1001],"capacity":0.05},{"talentKeyId":200104,"talentKeyType":1,"isEquip":1,"talentKeyName":{"id":"1079"},"battleSkillId":10010903,"keyName":{"id":"1218"},"keyTips":{"id":"1219"},"gunId":[1001],"capacity":0.05},{"talentKeyId":200105,"talentKeyType":1,"isEquip":1,"talentKeyName":{"id":"1079"},"battleSkillId":10010901,"keyName":{"id":"1220"},"keyTips":{"id":"1221"},"gunId":[1001],"capacity":0.05,"isSwitch":1,"replaceId":100104},{"talentKeyId":200106,"talentKeyType":1,"isEquip":1,"talentKeyName":{"id":"1079"},"battleSkillId":10010906,"keyName":{"id":"1222"},"keyTips":{"id":"1223"},"gunId":[1001],"capacity":0.05,"isSwitch":1,"replaceId":100107},{"talentKeyId":202101,"talentKeyType":1,"isEquip":1,"talentKeyName":{"id":"1079"},"battleSkillId":10210901,"keyName":{"id":"1224"},"keyTips":{"id":"1081"},"gunId":[1021],"capacity":0.05},{"talentKeyId":202102,"talentKeyType":1,"isEquip":1,"talentKeyName":{"id":"1079"},"battleSkillId":10210904,"keyName":{"id":"1225"},"keyTips":{"id":"1226"},"gunId":[1021],"capacity":0.05},{"talentKeyId":202103,"talentKeyType":1,"isEquip":1,"talentKeyName":{"id":"1079"},"battleSkillId":10210903,"keyName":{"id":"1227"},"keyTips":{"id":"1228"},"gunId":[1021],"capacity":0.05},{"talentKeyId":202104,"talentKeyType":1,"isEquip":1,"talentKeyName":{"id":"1079"},"battleSkillId":10210906,"keyName":{"id":"1229"},"keyTips":{"id":"1230"},"gunId":[1021],"capacity":0.05,"isSwitch":1,"replaceId":102107},{"talentKeyId":202105,"talentKeyType":1,"isEquip":1,"talentKeyName":{"id":"1079"},"battleSkillId":10210905,"keyName":{"id":"1231"},"keyTips":{"id":"1232"},"gunId":[1021],"capacity":0.05,"isSwitch":1,"replaceId":102105},{"talentKeyId":202106,"talentKeyType":1,"isEquip":1,"talentKeyName":{"id":"1079"},"battleSkillId":10210902,"keyName":{"id":"1233"},"keyTips":{"id":"1234"},"gunId":[1021],"capacity":0.05},{"talentKeyId":202501,"talentKeyType":1,"isEquip":1,"talentKeyName":{"id":"1079"},"battleSkillId":10250904,"keyName":{"id":"1235"},"keyTips":{"id":"1236"},"gunId":[1025],"capacity":0.05},{"talentKeyId":202502,"talentKeyType":1,"isEquip":1,"talentKeyName":{"id":"1079"},"battleSkillId":10250905,"keyName":{"id":"1237"},"keyTips":{"id":"1238"},"gunId":[1025],"capacity":0.05,"isSwitch":1,"replaceId":102505},{"talentKeyId":202503,"talentKeyType":1,"isEquip":1,"talentKeyName":{"id":"1079"},"battleSkillId":10250903,"keyName":{"id":"1239"},"keyTips":{"id":"1240"},"gunId":[1025],"capacity":0.05},{"talentKeyId":202504,"talentKeyType":1,"isEquip":1,"talentKeyName":{"id":"1079"},"battleSkillId":10250906,"keyName":{"id":"1241"},"keyTips":{"id":"1242"},"gunId":[1025],"capacity":0.05,"isSwitch":1,"replaceId":102507},{"talentKeyId":202505,"talentKeyType":1,"isEquip":1,"talentKeyName":{"id":"1079"},"battleSkillId":10250901,"keyName":{"id":"1243"},"keyTips":{"id":"1244"},"gunId":[1025],"capacity":0.05},{"talentKeyId":202506,"talentKeyType":1,"isEquip":1,"talentKeyName":{"id":"1079"},"battleSkillId":10250902,"keyName":{"id":"1245"},"keyTips":{"id":"1246"},"gunId":[1025],"capacity":0.05}]}